odoo/addons/product_mrp_info/README.rst
odoo/addons/product_mrp_info/__init__.py
odoo/addons/product_mrp_info/__manifest__.py
odoo/addons/product_mrp_info/i18n/es.po
odoo/addons/product_mrp_info/i18n/it.po
odoo/addons/product_mrp_info/i18n/product_mrp_info.pot
odoo/addons/product_mrp_info/models/__init__.py
odoo/addons/product_mrp_info/models/product.py
odoo/addons/product_mrp_info/readme/CONTRIBUTORS.rst
odoo/addons/product_mrp_info/readme/DESCRIPTION.rst
odoo/addons/product_mrp_info/readme/USAGE.rst
odoo/addons/product_mrp_info/static/description/icon.png
odoo/addons/product_mrp_info/static/description/index.html
odoo/addons/product_mrp_info/tests/__init__.py
odoo/addons/product_mrp_info/tests/test_product_mrp_info.py
odoo/addons/product_mrp_info/views/product_views.xml
odoo_addon_product_mrp_info-16.0.1.0.0.2.dist-info/METADATA
odoo_addon_product_mrp_info-16.0.1.0.0.2.dist-info/WHEEL
odoo_addon_product_mrp_info-16.0.1.0.0.2.dist-info/top_level.txt
odoo_addon_product_mrp_info-16.0.1.0.0.2.dist-info/RECORD
