Metadata-Version: 2.1
Name: odoo-addon-product_mrp_info
Version: 16.0.1.0.0.2
Summary: Adds smart button in product form view linking to manufacturing order list.
Home-page: https://github.com/OCA/manufacture
Author: ForgeFlow, Odoo Community Association (OCA)
Author-email: support@odoo-community.org
License: LGPL-3
Classifier: Programming Language :: Python
Classifier: Framework :: Odoo
Classifier: Framework :: Odoo :: 16.0
Classifier: License :: OSI Approved :: GNU Lesser General Public License v3 (LGPLv3)
Classifier: Development Status :: 4 - Beta
Requires-Python: >=3.10
Requires-Dist: odoo <16.1dev,>=16.0a
